{"skeleton":{"hash":"/wgsxOL5p6e2Ma/CwI3KY5Igb90","spine":"3.8.99","images":"","audio":"C:/Users/Admin/Desktop/Fx Cut/bullet/niepan_bullet"},"bones":[{"name":"root"},{"name":"bone40","parent":"root","scaleX":2,"scaleY":2},{"name":"glow","parent":"bone40","scaleX":0.8,"scaleY":0.8},{"name":"bo","parent":"bone40","rotation":-90,"x":9.19,"scaleX":0.673,"scaleY":0.673},{"name":"bo2","parent":"bone40","rotation":-90,"x":9.19,"scaleX":0.673,"scaleY":0.673},{"name":"bone","parent":"bone40","scaleX":0.7,"scaleY":0.7},{"name":"bone38","parent":"bone40"},{"name":"bone39","parent":"bone40","scaleX":4.13,"scaleY":4.13},{"name":"fast","parent":"bone40","scaleX":0.717,"scaleY":0.897},{"name":"fire","parent":"bone40"},{"name":"gq","parent":"bone40","scaleX":0.282},{"name":"gq2","parent":"bone40","scaleX":0.282},{"name":"bling","parent":"bone40"},{"name":"smoky","parent":"bone40"},{"name":"bone10","parent":"bling"},{"name":"bone12","parent":"bling"},{"name":"bone14","parent":"bling"},{"name":"bone16","parent":"bling"},{"name":"bone18","parent":"bling"},{"name":"bone20","parent":"bling"},{"name":"bone22","parent":"bling"},{"name":"bone24","parent":"bling"},{"name":"bone26","parent":"smoky"},{"name":"bone28","parent":"smoky"},{"name":"bone3","parent":"fast"},{"name":"bone30","parent":"smoky"},{"name":"bone32","parent":"smoky"},{"name":"bone34","parent":"smoky"},{"name":"bone36","parent":"smoky"},{"name":"bone4","parent":"fast"},{"name":"bone6","parent":"fast"},{"name":"bone8","parent":"bling"},{"name":"bone11","parent":"bone10","scaleX":1.355,"scaleY":1.355},{"name":"bone13","parent":"bone12","scaleX":1.355,"scaleY":1.355},{"name":"bone15","parent":"bone14","scaleX":1.355,"scaleY":1.355},{"name":"bone17","parent":"bone16","scaleX":1.355,"scaleY":1.355},{"name":"bone19","parent":"bone18","scaleX":1.355,"scaleY":1.355},{"name":"bone2","parent":"bone3","rotation":90,"scaleY":1.2},{"name":"bone21","parent":"bone20","scaleX":1.355,"scaleY":1.355},{"name":"bone23","parent":"bone22","scaleX":1.355,"scaleY":1.355},{"name":"bone25","parent":"bone24","scaleX":1.355,"scaleY":1.355},{"name":"bone27","parent":"bone26","rotation":58.75,"scaleX":1.508,"scaleY":1.508},{"name":"bone29","parent":"bone28","rotation":-120.61,"scaleX":1.508,"scaleY":1.508},{"name":"bone31","parent":"bone30","scaleX":1.508,"scaleY":1.508},{"name":"bone33","parent":"bone32","rotation":108.62,"scaleX":1.508,"scaleY":1.508},{"name":"bone35","parent":"bone34","scaleX":1.508,"scaleY":1.508},{"name":"bone37","parent":"bone36","rotation":-117.7,"scaleX":1.508,"scaleY":1.508},{"name":"bone5","parent":"bone4","rotation":90,"scaleY":1.2},{"name":"bone7","parent":"bone6","rotation":90,"scaleY":1.2},{"name":"bone9","parent":"bone8","scaleX":1.355,"scaleY":1.355}],"slots":[{"name":"DustGreen","bone":"bone27"},{"name":"DustGreen2","bone":"bone29"},{"name":"DustGreen3","bone":"bone31"},{"name":"DustGreen4","bone":"bone33"},{"name":"DustGreen5","bone":"bone35"},{"name":"DustGreen6","bone":"bone37"},{"name":"GlowPink","bone":"bone39","blend":"additive"},{"name":"1","bone":"bone"},{"name":"2","bone":"bone","blend":"additive"},{"name":"flash","bone":"bone2","blend":"additive"},{"name":"flash2","bone":"bone5","blend":"additive"},{"name":"flash3","bone":"bone7","blend":"additive"},{"name":"eff","bone":"bo","blend":"additive"},{"name":"eff2","bone":"bo2","blend":"additive"},{"name":"sdfa","bone":"gq","blend":"additive"},{"name":"sdfa2","bone":"gq2","blend":"additive"},{"name":"bling","bone":"bone9","blend":"additive"},{"name":"bling2","bone":"bone11","blend":"additive"},{"name":"bling3","bone":"bone13","blend":"additive"},{"name":"bling4","bone":"bone15","blend":"additive"},{"name":"bling5","bone":"bone17","blend":"additive"},{"name":"bling6","bone":"bone19","blend":"additive"},{"name":"bling7","bone":"bone21","blend":"additive"},{"name":"bling8","bone":"bone23","blend":"additive"},{"name":"bling9","bone":"bone25","blend":"additive"},{"name":"77-1","bone":"glow","blend":"additive"},{"name":"77-2","bone":"bone38","blend":"additive"},{"name":"baodian","bone":"fire","blend":"additive"}],"skins":[{"name":"default","attachments":{"77-1":{"77-1":{"width":128,"height":128}},"77-2":{"77-1":{"scaleX":0.8,"scaleY":0.8,"width":128,"height":128}},"DustGreen":{"DustGreen":{"width":80,"height":80}},"DustGreen2":{"DustGreen":{"width":80,"height":80}},"DustGreen3":{"DustGreen":{"width":80,"height":80}},"DustGreen4":{"DustGreen":{"width":80,"height":80}},"DustGreen5":{"DustGreen":{"width":80,"height":80}},"DustGreen6":{"DustGreen":{"width":80,"height":80}},"baodian":{"flash_windShard_fire":{"width":80,"height":80}},"bling":{"bling":{"width":30,"height":30}},"bling2":{"bling":{"width":30,"height":30}},"bling3":{"bling":{"width":30,"height":30}},"bling4":{"bling":{"width":30,"height":30}},"bling5":{"bling":{"width":30,"height":30}},"bling6":{"bling":{"width":30,"height":30}},"bling7":{"bling":{"width":30,"height":30}},"bling8":{"bling":{"width":30,"height":30}},"bling9":{"bling":{"width":30,"height":30}}}}],"animations":{"action":{"slots":{"77-1":{"attachment":[{"name":"77-1"}]},"77-2":{"color":[{"color":"ffffff00"},{"time":0.0667,"color":"c400ffff"},{"time":0.1667,"color":"ffffff00"}],"attachment":[{"name":"77-1"}]},"DustGreen":{"color":[{"color":"ffffff00","curve":"stepped"},{"time":0.0667,"color":"ffffff00"},{"time":0.3333,"color":"ffffffff"},{"time":0.7,"color":"ffffff00"}],"attachment":[{"name":"DustGreen"}]},"DustGreen2":{"color":[{"color":"ffffff00","curve":"stepped"},{"time":0.0667,"color":"ffffff00"},{"time":0.3333,"color":"ffffffff"},{"time":0.8,"color":"ffffff00"}],"attachment":[{"name":"DustGreen"}]},"DustGreen3":{"color":[{"color":"ffffff00","curve":"stepped"},{"time":0.0667,"color":"ffffff00"},{"time":0.3333,"color":"ffffffff"},{"time":0.8333,"color":"ffffff00"}],"attachment":[{"name":"DustGreen"}]},"DustGreen4":{"color":[{"color":"ffffff00","curve":"stepped"},{"time":0.0667,"color":"ffffff00"},{"time":0.3333,"color":"ffffffff"},{"time":0.7,"color":"ffffff00"}],"attachment":[{"name":"DustGreen"}]},"DustGreen5":{"color":[{"color":"ffffff00","curve":"stepped"},{"time":0.0667,"color":"ffffff00"},{"time":0.3333,"color":"ffffffff"},{"time":0.7333,"color":"ffffff00"}],"attachment":[{"name":"DustGreen"}]},"DustGreen6":{"color":[{"color":"ffffff00","curve":"stepped"},{"time":0.0667,"color":"ffffff00"},{"time":0.3333,"color":"ffffffff"},{"time":0.7667,"color":"ffffff00"}],"attachment":[{"name":"DustGreen"}]},"baodian":{"color":[{"color":"ffffff00","curve":"stepped"},{"time":0.0333,"color":"ffffff00"},{"time":0.1,"color":"ffffffff"},{"time":0.3333,"color":"ffffff00"}],"attachment":[{"name":"flash_windShard_fire"}]},"bling":{"color":[{"color":"ffae00ff"}],"attachment":[{"name":"bling"}]},"bling2":{"attachment":[{"name":"bling"}]},"bling3":{"attachment":[{"name":"bling"}]},"bling4":{"color":[{"color":"ffae00ff"}],"attachment":[{"name":"bling"}]},"bling5":{"attachment":[{"name":"bling"}]},"bling6":{"attachment":[{"name":"bling"}]},"bling7":{"color":[{"color":"ffae00ff"}],"attachment":[{"name":"bling"}]},"bling8":{"attachment":[{"name":"bling"}]},"bling9":{"attachment":[{"name":"bling"}]}},"bones":{"glow":{"scale":[{},{"time":0.0333,"x":0.596,"y":0.596},{"time":0.1,"x":1.623,"y":1.623},{"time":0.2333,"x":0,"y":0}]},"bone27":{"rotate":[{},{"time":0.1667,"angle":-45.54},{"time":0.7,"angle":-86.02}],"scale":[{},{"time":0.7,"x":3.305,"y":3.305}]},"bone29":{"rotate":[{},{"time":0.1667,"angle":-38.71},{"time":0.8,"angle":-86.02}],"translate":[{},{"time":0.1667,"x":1.66,"y":35.88},{"time":0.8,"x":3.69,"y":79.73}],"scale":[{},{"time":0.8,"x":1.329,"y":1.329}]},"bone31":{"rotate":[{},{"time":0.1667,"angle":-36.86},{"time":0.8333,"angle":-86.02}],"translate":[{},{"time":0.1667,"x":1.58,"y":34.17},{"time":0.8333,"x":3.69,"y":79.73}],"scale":[{},{"time":0.8333,"x":1.329,"y":1.329}]},"bone33":{"rotate":[{},{"time":0.1667,"angle":-45.54},{"time":0.7,"angle":-86.02}],"translate":[{},{"time":0.1667,"x":1.95,"y":42.21},{"time":0.7,"x":3.69,"y":79.73}],"scale":[{},{"time":0.7,"x":1.329,"y":1.329}]},"bone35":{"rotate":[{},{"time":0.1667,"angle":-43.01},{"time":0.7333,"angle":-86.02}],"translate":[{},{"time":0.1667,"x":1.84,"y":39.86},{"time":0.7333,"x":3.69,"y":79.73}],"scale":[{},{"time":0.7333,"x":1.329,"y":1.329}]},"bone37":{"rotate":[{},{"time":0.1667,"angle":-40.75},{"time":0.7667,"angle":-86.02}],"translate":[{},{"time":0.1667,"x":1.75,"y":37.76},{"time":0.7667,"x":3.69,"y":79.73}],"scale":[{},{"time":0.7667,"x":1.329,"y":1.329}]},"fire":{"rotate":[{"angle":-64.51}],"scale":[{"x":0,"y":0,"curve":"stepped"},{"time":0.0333,"x":0,"y":0},{"time":0.1,"x":1.462,"y":1.462},{"time":0.3333,"x":4.113,"y":4.113}]},"bone9":{"rotate":[{"time":0.1},{"time":0.5333,"angle":-24.93}],"translate":[{"time":0.1},{"time":0.2333,"y":64.53},{"time":0.5333,"y":106.02}],"scale":[{"x":0,"y":0,"curve":"stepped"},{"time":0.1,"x":0,"y":0},{"time":0.2333,"x":1.551,"y":1.551},{"time":0.5333,"x":0,"y":0}]},"bone11":{"rotate":[{"time":0.1},{"time":0.6,"angle":-44.11}],"translate":[{"time":0.1},{"time":0.2333,"y":64.53},{"time":0.6,"y":106.02}],"scale":[{"x":0,"y":0,"curve":"stepped"},{"time":0.1,"x":0,"y":0},{"time":0.2333,"x":1.551,"y":1.551},{"time":0.6,"x":0,"y":0}]},"bone13":{"rotate":[{"time":0.1},{"time":0.5667,"angle":12.43}],"translate":[{"time":0.1},{"time":0.2333,"y":64.53},{"time":0.5667,"y":106.02}],"scale":[{"x":0,"y":0,"curve":"stepped"},{"time":0.1,"x":0,"y":0},{"time":0.2333,"x":1.551,"y":1.551},{"time":0.5667,"x":0,"y":0}]},"bone15":{"rotate":[{"time":0.1},{"time":0.5,"angle":-44.11}],"translate":[{"time":0.1},{"time":0.2333,"y":64.53},{"time":0.5,"y":106.02}],"scale":[{"x":0,"y":0,"curve":"stepped"},{"time":0.1,"x":0,"y":0},{"time":0.2333,"x":1.551,"y":1.551},{"time":0.5,"x":0,"y":0}]},"bone17":{"rotate":[{"time":0.1},{"time":0.6,"angle":-44.11}],"translate":[{"time":0.1},{"time":0.2333,"y":64.53},{"time":0.6,"y":106.02}],"scale":[{"x":0,"y":0,"curve":"stepped"},{"time":0.1,"x":0,"y":0},{"time":0.2333,"x":1.551,"y":1.551},{"time":0.6,"x":0,"y":0}]},"bone19":{"rotate":[{"time":0.1},{"time":0.6,"angle":12.43}],"translate":[{"time":0.1},{"time":0.2333,"y":64.53},{"time":0.6,"y":106.02}],"scale":[{"x":0,"y":0,"curve":"stepped"},{"time":0.1,"x":0,"y":0},{"time":0.2333,"x":1.551,"y":1.551},{"time":0.6,"x":0,"y":0}]},"bone21":{"rotate":[{"time":0.1},{"time":0.6,"angle":-24.93}],"translate":[{"time":0.1},{"time":0.2333,"y":64.53},{"time":0.6,"y":106.02}],"scale":[{"x":0,"y":0,"curve":"stepped"},{"time":0.1,"x":0,"y":0},{"time":0.2333,"x":1.551,"y":1.551},{"time":0.6,"x":0,"y":0}]},"bone23":{"rotate":[{"time":0.1},{"time":0.6,"angle":12.43}],"translate":[{"time":0.1},{"time":0.2333,"y":64.53},{"time":0.6,"y":106.02}],"scale":[{"x":0,"y":0,"curve":"stepped"},{"time":0.1,"x":0,"y":0},{"time":0.2333,"x":1.551,"y":1.551},{"time":0.6,"x":0,"y":0}]},"bone25":{"rotate":[{"time":0.1},{"time":0.6,"angle":-44.11}],"translate":[{"time":0.1},{"time":0.2333,"y":64.53},{"time":0.6,"y":106.02}],"scale":[{"x":0,"y":0,"curve":"stepped"},{"time":0.1,"x":0,"y":0},{"time":0.2333,"x":1.551,"y":1.551},{"time":0.6,"x":0,"y":0}]},"bone14":{"rotate":[{"angle":46.11}],"scale":[{"x":0.636,"y":0.636}]},"bone8":{"rotate":[{"angle":-32.25}]},"bone16":{"rotate":[{"angle":88.88}]},"bone20":{"rotate":[{"angle":141.9}],"scale":[{"x":0.561,"y":0.561}]},"bone22":{"rotate":[{"angle":-130.39}],"scale":[{"x":0.773,"y":0.773}]},"bone24":{"rotate":[{"angle":-69.1}]},"bone10":{"rotate":[{"angle":-102.2}],"scale":[{"x":0.539,"y":0.539}]},"bone12":{"rotate":[{"angle":-165.85}]},"bone18":{"scale":[{"x":0.823,"y":0.823}]},"bone26":{"rotate":[{"angle":-63.39}],"scale":[{"x":1.297,"y":1.297}]},"bone28":{"rotate":[{"angle":-91.27}],"scale":[{"x":1.056,"y":1.056}]},"bone30":{"rotate":[{"angle":101.56}],"scale":[{"x":1.297,"y":1.297}]},"bone32":{"rotate":[{"angle":69.74}],"scale":[{"x":1.264,"y":1.264}]},"bone34":{"rotate":[{"angle":42.91}],"scale":[{"x":0.695,"y":0.695}]},"bone36":{"scale":[{"x":1.297,"y":1.297}]}}},"idle":{}}}