{
  "__type__": "cc.Mesh",
  "_name": "",
  "_objFlags": 0,
  "_native": ".bin",
  "_struct": {
    "primitives": [
      {
        "primitiveMode": 7,
        "vertexBundelIndices": [
          0
        ],
        "indexView": {
          "offset": 29808,
          "length": 5232,
          "count": 1308,
          "stride": 4
        }
      }
    ],
    "vertexBundles": [
      {
        "view": {
          "offset": 0,
          "length": 29808,
          "count": 621,
          "stride": 48
        },
        "attributes": [
          {
            "name": "a_position",
            "format": 32,
            "isNormalized": false
          },
          {
            "name": "a_normal",
            "format": 32,
            "isNormalized": false
          },
          {
            "name": "a_texCoord",
            "format": 21,
            "isNormalized": false
          },
          {
            "name": "a_tangent",
            "format": 44,
            "isNormalized": false
          }
        ]
      }
    ],
    "minPosition": {
      "__type__": "cc.Vec3",
      "x": -0.0000030142036848701537,
      "y": -0.004891011863946915,
      "z": -0.0004577742947731167
    },
    "maxPosition": {
      "__type__": "cc.Vec3",
      "x": 0.007088955491781235,
      "y": 0.004727735184133053,
      "z": 0.0005001708050258458
    }
  },
  "_hash": 191629641
}