{
  "__type__": "cc.TextAsset",
  "_name": "skeleton.atlas",
  "_objFlags": 0,
  "_native": "",
  "text": "\nskeleton.png\nsize: 512,512\nformat: RGBA8888\nfilter: Linear,Linear\nrepeat: none\nfish_fillet1\n  rotate: false\n  xy: 2, 100\n  size: 152, 123\n  orig: 152, 123\n  offset: 0, 0\n  index: -1\nfish_fillet2\n  rotate: true\n  xy: 328, 317\n  size: 152, 141\n  orig: 152, 141\n  offset: 0, 0\n  index: -1\nfish_fillet3\n  rotate: true\n  xy: 328, 171\n  size: 144, 129\n  orig: 144, 129\n  offset: 0, 0\n  index: -1\nfishbone\n  rotate: false\n  xy: 2, 225\n  size: 324, 244\n  orig: 338, 254\n  offset: 4, 5\n  index: -1\n"
}